earthquake_selection-1.0.0.dist-info/licenses/LICENSE
selection_service/__init__.py
selection_service/core/Config.py
selection_service/core/ErrorHandle.py
selection_service/core/LoggingConfig.py
selection_service/core/Pipeline.py
selection_service/core/__init__.py
selection_service/data/NGA-West2_flatfile.csv
selection_service/data/stations.xlsx
selection_service/enums/Enums.py
selection_service/enums/__init__.py
selection_service/processing/Mappers.py
selection_service/processing/ResultHandle.py
selection_service/processing/Selection.py
selection_service/processing/__init__.py
selection_service/providers/AfadProvider.py
selection_service/providers/FdsnProvider.py
selection_service/providers/IProvider.py
selection_service/providers/PeerProvider.py
selection_service/providers/ProvidersFactory.py
selection_service/providers/__init__.py
selection_service/utility/__init__.py
selection_service/utility/convertPeerFlatfile.py
selection_service/utility/path_utils.py
earthquake_selection-1.0.0.dist-info/METADATA
earthquake_selection-1.0.0.dist-info/WHEEL
earthquake_selection-1.0.0.dist-info/top_level.txt
earthquake_selection-1.0.0.dist-info/RECORD
