Metadata-Version: 2.4
Name: earthquake_selection
Version: 1.0.0
Summary: A library for earthquake selection
Author-email: Muhammed Sural <muhammedsural@gmail.com>
License: MIT License
Project-URL: Homepage, https://github.com/muhammedsural/SELECTIONEARTHQUAKE
Project-URL: Documentation, https://muhammedsural.github.io/SELECTIONEARTHQUAKE
Project-URL: Repository, https://github.com/muhammedsural/SELECTIONEARTHQUAKE
Project-URL: Issues, https://github.com/muhammedsural/SELECTIONEARTHQUAKE/issues
Project-URL: Changelog, https://github.com/muhammedsural/SELECTIONEARTHQUAKE/releases
Keywords: earthquake,seismology,data-processing,selection,peer,nga,afad
Classifier: Development Status :: 4 - Beta
Classifier: Intended Audience :: Science/Research
Classifier: License :: OSI Approved :: MIT License
Classifier: Programming Language :: Python :: 3
Classifier: Programming Language :: Python :: 3.10
Classifier: Programming Language :: Python :: 3.11
Classifier: Programming Language :: Python :: 3.12
Classifier: Programming Language :: Python :: 3.13
Classifier: Topic :: Scientific/Engineering
Classifier: Topic :: Scientific/Engineering :: Physics
Requires-Python: >=3.10
License-File: LICENSE
Requires-Dist: numpy>=2.2.6
Requires-Dist: pandas>=2.3.2
Requires-Dist: scipy>=1.15.3
Requires-Dist: requests>=2.32.5
Requires-Dist: aiohttp>=3.12.15
Requires-Dist: obspy>=1.4.2
Requires-Dist: openpyxl>=3.1.5
Requires-Dist: pyyaml>=6.0
Requires-Dist: tqdm>=4.65.0
Provides-Extra: dev
Requires-Dist: pytest>=8.0.0; extra == "dev"
Requires-Dist: pytest-cov>=4.1.0; extra == "dev"
Requires-Dist: pytest-asyncio>=0.21.0; extra == "dev"
Requires-Dist: black>=23.0.0; extra == "dev"
Requires-Dist: flake8>=7.0.0; extra == "dev"
Requires-Dist: isort>=5.12.0; extra == "dev"
Requires-Dist: sphinx>=7.0.0; extra == "dev"
Requires-Dist: sphinx-rtd-theme>=2.0.0; extra == "dev"
Requires-Dist: twine>=5.0.0; extra == "dev"
Dynamic: license-file
